s3sourceuploader.py
setup.py
s3sourceuploader.egg-info/PKG-INFO
s3sourceuploader.egg-info/SOURCES.txt
s3sourceuploader.egg-info/dependency_links.txt
s3sourceuploader.egg-info/entry_points.txt
s3sourceuploader.egg-info/requires.txt
s3sourceuploader.egg-info/top_level.txt