Metadata-Version: 1.0
Name: s3sourceuploader
Version: 0.1.2
Summary: Add an upload to s3 command to setuptools.
Home-page: http://github.com/pbs/s3sourceuploader
Author: Sever Banesiu
Author-email: banesiu.sever@gmail.com
License: BSD
Keywords: setuptools s3 upload
Platform: UNKNOWN
